hyper_param_opt
